loglead/OOV_detector.py
loglead/RarityModel.py
loglead/__init__.py
loglead/anomaly_detection.py
loglead/explainer.py
loglead/next_event_prediction.py
loglead/enhancers/__init__.py
loglead/enhancers/eventlog.py
loglead/enhancers/sequence.py
loglead/loaders/__init__.py
loglead/loaders/adfa.py
loglead/loaders/awsctd.py
loglead/loaders/base.py
loglead/loaders/bgl.py
loglead/loaders/gelf.py
loglead/loaders/hadoop.py
loglead/loaders/hdfs.py
loglead/loaders/lo2.py
loglead/loaders/nezha.py
loglead/loaders/pro.py
loglead/loaders/raw.py
loglead/loaders/supercomputers.py
loglead/parsers/README.md
loglead/parsers/__init__.py
loglead/parsers/AEL/AEL.py
loglead/parsers/AEL/LICENSE
loglead/parsers/AEL/README.md
loglead/parsers/Brain/Brain.py
loglead/parsers/Brain/LICENSE
loglead/parsers/Brain/README.md
loglead/parsers/bert/README.md
loglead/parsers/bert/bertembedding.py
loglead/parsers/drain3/LICENSE
loglead/parsers/drain3/README.md
loglead/parsers/drain3/drain.py
loglead/parsers/drain3/drain3.ini
loglead/parsers/drain3/drain3_no_masking.ini
loglead/parsers/iplom/IPLoM.py
loglead/parsers/iplom/LICENSE
loglead/parsers/iplom/README.md
loglead/parsers/lenma/LICENSE
loglead/parsers/lenma/README.md
loglead/parsers/lenma/lenma.py
loglead/parsers/pl_iplom/README.md
loglead/parsers/pl_iplom/pl_iplom.py
loglead/parsers/pyspell/LICENSE
loglead/parsers/pyspell/README.md
loglead/parsers/pyspell/spell.py
LogLead-1.2.1.dist-info/LICENSE
LogLead-1.2.1.dist-info/METADATA
LogLead-1.2.1.dist-info/WHEEL
LogLead-1.2.1.dist-info/top_level.txt
LogLead-1.2.1.dist-info/RECORD
