Metadata-Version: 2.1
Name: LogLead
Version: 1.2.1
Summary: LogLead stands for Log Loader, Enhancer, and Anomaly Detector
Author-email: Mika Mäntylä <mika.mantyla@helsinki.fi>, Jesse Nyyssölä <jesse.nyyssola@helsinki.fi>, Yuqing Wang <yuqing.wang@helsinki.fi>, Alexander Bakhtin <alexander.bakhtin@protonmail.com>
Maintainer-email: Alexander Bakhtin <alexander.bakhtin@protonmail.com>
License: MIT License
Project-URL: Homepage, https://github.com/EvoTestOps/LogLead
Keywords: logs,anomaly detection,log parsing
Classifier: Development Status :: 4 - Beta
Classifier: Intended Audience :: Education
Classifier: Intended Audience :: Science/Research
Classifier: Intended Audience :: Information Technology
Classifier: License :: OSI Approved :: MIT License
Classifier: Programming Language :: Python :: 3
Classifier: Programming Language :: Python :: 3.9
Classifier: Programming Language :: Python :: 3.10
Classifier: Programming Language :: Python :: 3.11
Classifier: Programming Language :: Python :: 3.12
Classifier: Topic :: Scientific/Engineering :: Mathematics
Classifier: Topic :: Software Development :: Libraries :: Python Modules
Classifier: Topic :: System :: Logging
Requires-Python: <3.13,>=3.9
License-File: LICENSE
Requires-Dist: polars[numpy,pandas,pyarrow]>=1.5
Requires-Dist: scipy>=1.10.1
Requires-Dist: regex>=2023.10.3
Requires-Dist: drain3>=0.9.11
Requires-Dist: tipping>=0.1.3
Requires-Dist: scikit-learn>=1.2.2
Requires-Dist: xgboost>=1.7.3
Requires-Dist: python-dotenv>=1.0.1
Requires-Dist: pyyaml
Requires-Dist: psutil
Requires-Dist: jinja2
Requires-Dist: matplotlib
Requires-Dist: requests
Requires-Dist: tqdm
Requires-Dist: GitPython
Requires-Dist: py7zr
Requires-Dist: shap>=0.42.1
Requires-Dist: umap-learn>=0.5.6
Requires-Dist: plotly>=5.19.0
Requires-Dist: nbformat>=4.2.0
Requires-Dist: scikit-optimize>=0.10.1
